utils/Detector.py
utils/Models.py
utils/Run.py
utils/Transformer.py
utils/VideoRead.py
utils/__init__.py
SDDetector-0.1.0.dist-info/LICENSE
SDDetector-0.1.0.dist-info/METADATA
SDDetector-0.1.0.dist-info/WHEEL
SDDetector-0.1.0.dist-info/top_level.txt
SDDetector-0.1.0.dist-info/RECORD
