Metadata-Version: 2.1
Name: SDDetector
Version: 0.1.0
Summary: lightweight video detection
Home-page: https://github.com/thomascong121/SocialDistance
Author: SocialDistance model contributors
Author-email: thomascong@outlook.com
License: UNKNOWN
Platform: UNKNOWN
Classifier: Programming Language :: Python :: 3
Classifier: License :: OSI Approved :: MIT License
Classifier: Operating System :: OS Independent
Requires-Python: >=3.6
